mini_agent_harness/__init__.py
mini_agent_harness/cli.py
mini_agent_harness/core/__init__.py
mini_agent_harness/core/llm.py
mini_agent_harness/core/loop.py
mini_agent_harness/server.py
mini_agent_harness/testing/__init__.py
mini_agent_harness/testing/fixtures.py
mini_agent_harness/testing/plugin.py
mini_agent_harness/tools/__init__.py
mini_agent_harness/tools/echo.py
mini_agent_harness-0.2.0.dist-info/LICENSE
mini_agent_harness-0.2.0.dist-info/METADATA
mini_agent_harness-0.2.0.dist-info/WHEEL
mini_agent_harness-0.2.0.dist-info/entry_points.txt
mini_agent_harness-0.2.0.dist-info/RECORD
