Metadata-Version: 2.1
Name: mini-agent-harness
Version: 0.2.0
Summary: Small, test-first AI agent starter kit with built-in pytest harness.
License: MIT
Author: Haluk Sonmezler
Author-email: halukson@icloud.com
Requires-Python: >=3.9,<4.0
Classifier: License :: OSI Approved :: MIT License
Classifier: Programming Language :: Python :: 3
Classifier: Programming Language :: Python :: 3.9
Classifier: Programming Language :: Python :: 3.10
Classifier: Programming Language :: Python :: 3.11
Classifier: Programming Language :: Python :: 3.12
Provides-Extra: all
Provides-Extra: gemini
Provides-Extra: server
Requires-Dist: deepeval (>=0.20.5,<0.21.0) ; extra == "all"
Requires-Dist: fastapi (>=0.110.0,<0.111.0) ; extra == "all" or extra == "server"
Requires-Dist: google-generativeai (>=0.4.1,<0.5.0) ; extra == "all" or extra == "gemini"
Requires-Dist: guardrails-ai (>=0.4.0,<0.5.0) ; extra == "all"
Requires-Dist: langsmith (>=0.1.45,<0.2.0) ; extra == "all"
Requires-Dist: openai (>=1.25.0,<2.0.0) ; extra == "all"
Requires-Dist: pytest (>=8.2.0,<9.0.0)
Requires-Dist: python-multipart (>=0.0.9,<0.0.10) ; extra == "all" or extra == "server"
Requires-Dist: pyyaml (>=6.0,<7.0)
Requires-Dist: typer (>=0.9.0,<0.10.0)
Requires-Dist: uvicorn (>=0.29.0,<0.30.0) ; extra == "all" or extra == "server"
